pdffiller/__init__.py
pdffiller/__main__.py
pdffiller/_version.py
pdffiller/const.py
pdffiller/exceptions.py
pdffiller/pdf.py
pdffiller/py.typed.py
pdffiller/typing.py
pdffiller/utils.py
pdffiller/cli/__init__.py
pdffiller/cli/args.py
pdffiller/cli/boolean_action.py
pdffiller/cli/cli.py
pdffiller/cli/command.py
pdffiller/cli/exit_codes.py
pdffiller/cli/formatters.py
pdffiller/cli/once_argument.py
pdffiller/cli/smart_formatter.py
pdffiller/cli/commands/__init__.py
pdffiller/cli/commands/dump_data_fields.py
pdffiller/cli/commands/fill_form.py
pdffiller/io/__init__.py
pdffiller/io/colors.py
pdffiller/io/custom_pdf_writer.py
pdffiller/io/output.py
pdffiller/widgets/__init__.py
pdffiller/widgets/base.py
pdffiller/widgets/checkbox.py
pdffiller/widgets/radio.py
pdffiller/widgets/text.py
python_pdffiller-1.1.1.dist-info/licenses/AUTHORS.rst
python_pdffiller-1.1.1.dist-info/licenses/COPYING
python_pdffiller-1.1.1.dist-info/METADATA
python_pdffiller-1.1.1.dist-info/WHEEL
python_pdffiller-1.1.1.dist-info/entry_points.txt
python_pdffiller-1.1.1.dist-info/top_level.txt
python_pdffiller-1.1.1.dist-info/RECORD
