Metadata-Version: 2.4
Name: python-pdffiller
Version: 1.1.1
Summary: Interact with PDF by inspecting or filling it
Author-email: Jacques Raphanel <jraphanel@sismic.fr>
License-Expression: MIT
Project-URL: changelog, https://github.com/sismicfr/pypdffiller/blob/main/CHANGELOG.md
Project-URL: homepage, https://github.com/sismicfr/pypdffiller
Project-URL: issues, https://github.com/sismicfr/pypdffiller/issues
Project-URL: repository, http://github.com/sismicfr/pypdffiller.git
Keywords: development,pdf
Classifier: Development Status :: 5 - Production/Stable
Classifier: Environment :: Console
Classifier: Intended Audience :: Developers
Classifier: Natural Language :: English
Classifier: Operating System :: POSIX
Classifier: Operating System :: Microsoft :: Windows
Classifier: Programming Language :: Python :: 3
Classifier: Programming Language :: Python :: 3.9
Classifier: Programming Language :: Python :: 3.10
Classifier: Programming Language :: Python :: 3.11
Classifier: Programming Language :: Python :: 3.12
Classifier: Programming Language :: Python :: 3.13
Classifier: Programming Language :: Python :: 3.14
Requires-Python: >=3.9
License-File: COPYING
License-File: AUTHORS.rst
Requires-Dist: pypdf
Requires-Dist: colorama
Requires-Dist: pyyaml
Dynamic: license-file
